{
    "230.010-12": {
        "篇名": "杜甫 復愁十二首·其十二",
        "1": {
            "3": {
                "1": {
                    "1": "病",
                    "2": "減",
                    "3": "詩",
                    "4": "仍",
                    "5": "拙"
                },
                "2": {
                    "1": "吟",
                    "2": "多",
                    "3": "意",
                    "4": "有",
                    "5": "餘"
                }
            },
            "4": {
                "1": {
                    "1": "莫",
                    "2": "看",
                    "3": "江",
                    "4": "總",
                    "5": "老"
                },
                "2": {
                    "1": "猶",
                    "2": "被",
                    "3": "賞",
                    "4": "時",
                    "5": "魚"
                }
            }
        }
    }
}