{
    "447-087": {
        "3": {
            "1": {
                "1": "寫",
                "2": "了",
                "3": "吟",
                "4": "看",
                "5": "滿",
                "6": "卷",
                "7": "愁"
            },
            "2": {
                "1": "淺",
                "2": "紅",
                "3": "箋",
                "4": "紙",
                "5": "小",
                "6": "銀",
                "7": "鉤"
            }
        },
        "4": {
            "1": {
                "1": "未",
                "2": "容",
                "3": "寄",
                "4": "與",
                "5": "微",
                "6": "之",
                "7": "去"
            },
            "2": {
                "1": "已",
                "2": "被",
                "3": "人",
                "4": "傳",
                "5": "到",
                "6": "越",
                "7": "州"
            }
        }
    }
}
