{
    "447-009": {
        "3": {
            "1": {
                "1": "形",
                "2": "容",
                "3": "瘦",
                "4": "薄",
                "5": "詩",
                "6": "情",
                "7": "苦"
            },
            "2": {
                "1": "豈",
                "2": "是",
                "3": "人",
                "4": "間",
                "5": "有",
                "6": "相",
                "7": "人"
            }
        },
        "4": {
            "1": {
                "1": "只",
                "2": "合",
                "3": "一",
                "4": "生",
                "5": "眠",
                "6": "白",
                "7": "屋"
            },
            "2": {
                "1": "何",
                "2": "因",
                "3": "三",
                "4": "度",
                "5": "擁",
                "6": "朱",
                "7": "輪"
            }
        },
        "5": {
            "1": {
                "1": "金",
                "2": "章",
                "3": "未",
                "4": "佩",
                "5": "雖",
                "6": "非",
                "7": "貴"
            },
            "2": {
                "1": "銀",
                "2": "榼",
                "3": "常",
                "4": "攜",
                "5": "亦",
                "6": "不",
                "7": "貧"
            }
        },
        "6": {
            "1": {
                "1": "唯",
                "2": "是",
                "3": "無",
                "4": "兒",
                "5": "頭",
                "6": "早",
                "7": "白"
            },
            "2": {
                "1": "被",
                "2": "天",
                "3": "磨",
                "4": "折",
                "5": "恰",
                "6": "平",
                "7": "均"
            }
        }
    }
}
