{
    "03.18": {
        "篇名": "國風·衞風·伯兮",
        "1": {
            "3": {
                "1": {
                    "1": "伯",
                    "2": "兮",
                    "3": "朅",
                    "4": "兮"
                },
                "2": {
                    "1": "邦",
                    "2": "之",
                    "3": "桀",
                    "4": "兮"
                },
                "3": {
                    "1": "伯",
                    "2": "也",
                    "3": "執",
                    "4": "殳"
                },
                "4": {
                    "1": "爲",
                    "2": "王",
                    "3": "前",
                    "4": "驅"
                }
            }
        },
        "2": {
            "5": {
                "1": {
                    "1": "自",
                    "2": "伯",
                    "3": "之",
                    "4": "東"
                },
                "2": {
                    "1": "首",
                    "2": "如",
                    "3": "飛",
                    "4": "蓬"
                },
                "3": {
                    "1": "豈",
                    "2": "無",
                    "3": "膏",
                    "4": "沐"
                },
                "4": {
                    "1": "誰",
                    "2": "適",
                    "3": "爲",
                    "4": "容"
                }
            }
        },
        "3": {
            "7": {
                "1": {
                    "1": "其",
                    "2": "雨",
                    "3": "其",
                    "4": "雨"
                },
                "2": {
                    "1": "杲",
                    "2": "杲",
                    "3": "出",
                    "4": "日"
                },
                "3": {
                    "1": "願",
                    "2": "言",
                    "3": "思",
                    "4": "伯"
                },
                "4": {
                    "1": "甘",
                    "2": "心",
                    "3": "首",
                    "4": "疾"
                }
            }
        },
        "4": {
            "9": {
                "1": {
                    "1": "焉",
                    "2": "得",
                    "3": "諼",
                    "4": "草"
                },
                "2": {
                    "1": "言",
                    "2": "樹",
                    "3": "之",
                    "4": "背"
                },
                "3": {
                    "1": "願",
                    "2": "言",
                    "3": "思",
                    "4": "伯"
                },
                "4": {
                    "1": "使",
                    "2": "我",
                    "3": "心",
                    "4": "痗"
                }
            }
        }
    }
}