{
    "作者": "白居易",
    "詩題": "馴犀◯感爲政之難終也",
    "3": {
        "1": {
            "1": "馴",
            "2": "犀",
            "3": "馴",
            "4": "犀",
            "5": "通",
            "6": "天",
            "7": "犀"
        },
        "2": {
            "1": "軀",
            "2": "貌",
            "3": "駭",
            "4": "人",
            "5": "角",
            "6": "駭",
            "7": "雞"
        }
    },
    "4": {
        "1": {
            "1": "海",
            "2": "蠻",
            "3": "聞",
            "4": "有",
            "5": "明",
            "6": "天",
            "7": "子"
        },
        "2": {
            "1": "驅",
            "2": "犀",
            "3": "乘",
            "4": "傳",
            "5": "來",
            "6": "萬",
            "7": "里"
        }
    },
    "5": {
        "1": {
            "1": "一",
            "2": "朝",
            "3": "得",
            "4": "謁",
            "5": "大",
            "6": "明",
            "7": "宮"
        },
        "2": {
            "1": "歡",
            "2": "呼",
            "3": "拜",
            "4": "舞",
            "5": "自",
            "6": "論",
            "7": "功"
        }
    },
    "6": {
        "1": {
            "1": "五",
            "2": "年",
            "3": "馴",
            "4": "養",
            "5": "始",
            "6": "堪",
            "7": "獻"
        },
        "2": {
            "1": "六",
            "2": "譯",
            "3": "語",
            "4": "言",
            "5": "方",
            "6": "得",
            "7": "通"
        }
    },
    "7": {
        "1": {
            "1": "上",
            "2": "嘉",
            "3": "人",
            "4": "獸",
            "5": "俱",
            "6": "來",
            "7": "遠"
        },
        "2": {
            "1": "蠻",
            "2": "館",
            "3": "四",
            "4": "方",
            "5": "犀",
            "6": "入",
            "7": "苑"
        }
    },
    "8": {
        "1": {
            "1": "秣",
            "2": "以",
            "3": "瑤",
            "4": "芻",
            "5": "鎖",
            "6": "以",
            "7": "金"
        },
        "2": {
            "1": "故",
            "2": "鄕",
            "3": "迢",
            "4": "遞",
            "5": "君",
            "6": "門",
            "7": "深"
        }
    },
    "9": {
        "1": {
            "1": "海",
            "2": "鳥",
            "3": "不",
            "4": "知",
            "5": "鐘",
            "6": "鼓",
            "7": "樂"
        },
        "2": {
            "1": "池",
            "2": "魚",
            "3": "空",
            "4": "結",
            "5": "江",
            "6": "湖",
            "7": "心"
        }
    },
    "10": {
        "1": {
            "1": "馴",
            "2": "犀",
            "3": "生",
            "4": "處",
            "5": "南",
            "6": "方",
            "7": "熱"
        },
        "2": {
            "1": "秋",
            "2": "無",
            "3": "白",
            "4": "露",
            "5": "冬",
            "6": "無",
            "7": "雪"
        }
    },
    "11": {
        "1": {
            "1": "一",
            "2": "入",
            "3": "上",
            "4": "林",
            "5": "三",
            "6": "四",
            "7": "年"
        },
        "2": {
            "1": "又",
            "2": "逢",
            "3": "今",
            "4": "歲",
            "5": "苦",
            "6": "寒",
            "7": "月"
        }
    },
    "12": {
        "1": {
            "1": "飲",
            "2": "冰",
            "3": "臥",
            "4": "霰",
            "5": "苦",
            "6": "踡",
            "7": "跼"
        },
        "2": {
            "1": "角",
            "2": "骨",
            "3": "凍",
            "4": "傷",
            "5": "鱗",
            "6": "甲",
            "7": "蹜"
        }
    },
    "13": {
        "1": {
            "1": "馴",
            "2": "犀",
            "3": "死"
        },
        "2": {
            "1": "蠻",
            "2": "兒",
            "3": "啼"
        }
    },
    "14": {
        "1": {
            "1": "向",
            "2": "闕",
            "3": "再",
            "4": "拜",
            "5": "顏",
            "6": "色",
            "7": "低"
        }
    },
    "15": {
        "1": {
            "1": "奏",
            "2": "乞",
            "3": "生",
            "4": "歸",
            "5": "本",
            "6": "國",
            "7": "去"
        },
        "2": {
            "1": "恐",
            "2": "身",
            "3": "凍",
            "4": "死",
            "5": "似",
            "6": "馴",
            "7": "犀"
        }
    },
    "16": {
        "1": {
            "1": "君",
            "2": "不",
            "3": "見",
            "4": "建",
            "5": "中",
            "6": "初"
        },
        "2": {
            "1": "馴",
            "2": "象",
            "3": "生",
            "4": "還",
            "5": "放",
            "6": "林",
            "7": "邑"
        }
    },
    "17": {
        "1": {
            "1": "君",
            "2": "不",
            "3": "見",
            "4": "貞",
            "5": "元",
            "6": "年",
            "7": "末"
        },
        "2": {
            "1": "馴",
            "2": "犀",
            "3": "凍",
            "4": "死",
            "5": "蠻",
            "6": "兒",
            "7": "泣"
        }
    },
    "18": {
        "1": {
            "1": "所",
            "2": "嗟",
            "3": "建",
            "4": "中",
            "5": "異",
            "6": "貞",
            "7": "元"
        },
        "2": {
            "1": "象",
            "2": "生",
            "3": "犀",
            "4": "死",
            "5": "何",
            "6": "足",
            "7": "言"
        }
    }
}