{
    "23.01-02": {
        "篇名": "阮嗣宗 詠懷詩十七首·其二",
        "1": {
            "3": {
                "1": "二妃遊江濱",
                "2": "消遙順風翔"
            },
            "4": {
                "1": "交甫懷環珮",
                "2": "婉孌有芬芳"
            },
            "5": {
                "1": "猗靡情歡愛",
                "2": "千載不相忘"
            },
            "6": {
                "1": "傾城迷下蔡",
                "2": "容好結中腸"
            },
            "7": {
                "1": "感激生憂思",
                "2": "諼草樹蘭房"
            },
            "8": {
                "1": "膏沐爲誰施",
                "2": "其雨怨朝陽"
            },
            "9": {
                "1": "如何金石交",
                "2": "一旦更離傷"
            }
        }
    }
}