{
    "24.12-01": {
        "篇名": "陸士衡 答賈長淵[幷序]·其一",
        "1": {
            "3": {
                "1": "余昔爲太子洗馬",
                "2": "賈長淵以散騎常侍東宮積年",
                "3": "余出補吳王郎中令",
                "4": "元康六年入爲尙書郎",
                "5": "魯公贈詩一篇",
                "6": "作此詩答之云爾"
            }
        },
        "2": {
            "5": {
                "1": "伊昔有皇",
                "2": "肇濟黎蒸",
                "3": "先天創物",
                "4": "景命是膺",
                "5": "降及羣後",
                "6": "迭毀迭興",
                "7": "邈矣終古",
                "8": "崇替有徵"
            }
        }
    }
}