{
    "28.03-05": {
        "篇名": "鮑明遠 樂府八首·苦熱行",
        "1": {
            "3": {
                "1": "赤阪橫西阻",
                "2": "火山赫南威",
                "3": "身熱頭且痛",
                "4": "鳥墮魂來歸",
                "5": "湯泉發雲潭",
                "6": "焦煙起石圻",
                "7": "日月有恆昏",
                "8": "雨露未嘗晞",
                "9": "丹蛇踰百尺",
                "10": "玄蜂盈十圍",
                "11": "含沙射流影",
                "12": "吹蠱痛行暉",
                "13": "鄣氣晝熏體",
                "14": "菵露夜霑衣",
                "15": "飢猿莫下食",
                "16": "晨禽不敢飛",
                "17": "毒涇尙多死",
                "18": "渡瀘寧具腓",
                "19": "生軀蹈死地",
                "20": "昌志登禍機",
                "21": "戈船榮旣薄",
                "22": "伏波賞亦微",
                "23": "財輕君尙惜",
                "24": "士重安可希"
            }
        }
    }
}