{
    "31.09-30": {
        "篇名": "江文通 雜體詩三十首·休上人[別怨]",
        "1": {
            "3": {
                "1": "西北秋風至",
                "2": "楚客心悠哉",
                "3": "日暮碧雲合",
                "4": "佳人殊未來",
                "5": "露采方泛豔",
                "6": "月華始徘徊",
                "7": "寶書爲君掩",
                "8": "瑤琴詎能開",
                "9": "相思巫山渚",
                "10": "悵望陽雲臺",
                "11": "膏爐絕沈燎",
                "12": "綺席生浮埃",
                "13": "桂水日千里",
                "14": "因之平生懷"
            }
        }
    }
}