{
    "05": {
        "篇名": "論語·公冶長第五",
        "1": {
            "3": {
                "1": {
                    "1": "子",
                    "2": "謂",
                    "3": "公",
                    "4": "冶",
                    "5": "長"
                },
                "2": {
                    "1": "可",
                    "2": "妻",
                    "3": "也"
                },
                "3": {
                    "1": "雖",
                    "2": "在",
                    "3": "縲",
                    "4": "絏",
                    "5": "之",
                    "6": "中"
                },
                "4": {
                    "1": "非",
                    "2": "其",
                    "3": "罪",
                    "4": "也"
                },
                "5": {
                    "1": "以",
                    "2": "其",
                    "3": "子",
                    "4": "妻",
                    "5": "之"
                }
            }
        },
        "2": {
            "5": {
                "1": {
                    "1": "子",
                    "2": "謂",
                    "3": "南",
                    "4": "容"
                },
                "2": {
                    "1": "邦",
                    "2": "有",
                    "3": "道"
                },
                "3": {
                    "1": "不",
                    "2": "廢"
                },
                "4": {
                    "1": "邦",
                    "2": "無",
                    "3": "道"
                },
                "5": {
                    "1": "免",
                    "2": "於",
                    "3": "刑",
                    "4": "戮"
                },
                "6": {
                    "1": "以",
                    "2": "其",
                    "3": "兄",
                    "4": "之",
                    "5": "子",
                    "6": "妻",
                    "7": "之"
                }
            }
        },
        "3": {
            "7": {
                "1": {
                    "1": "子",
                    "2": "謂",
                    "3": "子",
                    "4": "賤"
                },
                "2": {
                    "1": "君",
                    "2": "子",
                    "3": "哉",
                    "4": "若",
                    "5": "人"
                },
                "3": {
                    "1": "魯",
                    "2": "無",
                    "3": "君",
                    "4": "子",
                    "5": "者"
                },
                "4": {
                    "1": "斯",
                    "2": "焉",
                    "3": "取",
                    "4": "斯"
                }
            }
        },
        "4": {
            "9": {
                "1": {
                    "1": "子",
                    "2": "貢",
                    "3": "問",
                    "4": "曰"
                },
                "2": {
                    "1": "賜",
                    "2": "也",
                    "3": "何",
                    "4": "如"
                },
                "3": {
                    "1": "子",
                    "2": "曰"
                },
                "4": {
                    "1": "女"
                },
                "5": {
                    "1": "器",
                    "2": "也"
                },
                "6": {
                    "1": "曰"
                },
                "7": {
                    "1": "何",
                    "2": "器",
                    "3": "也"
                },
                "8": {
                    "1": "曰"
                },
                "9": {
                    "1": "瑚",
                    "2": "璉",
                    "3": "也"
                }
            }
        },
        "5": {
            "11": {
                "1": {
                    "1": "或",
                    "2": "曰"
                },
                "2": {
                    "1": "雍",
                    "2": "也",
                    "3": "仁",
                    "4": "而",
                    "5": "不",
                    "6": "佞"
                },
                "3": {
                    "1": "子",
                    "2": "曰"
                },
                "4": {
                    "1": "焉",
                    "2": "用",
                    "3": "佞"
                },
                "5": {
                    "1": "禦",
                    "2": "人",
                    "3": "以",
                    "4": "口",
                    "5": "給"
                },
                "6": {
                    "1": "屢",
                    "2": "憎",
                    "3": "於",
                    "4": "人"
                },
                "7": {
                    "1": "不",
                    "2": "知",
                    "3": "其",
                    "4": "仁"
                },
                "8": {
                    "1": "焉",
                    "2": "用",
                    "3": "佞"
                }
            }
        },
        "6": {
            "13": {
                "1": {
                    "1": "子",
                    "2": "使",
                    "3": "漆",
                    "4": "雕",
                    "5": "開",
                    "6": "仕"
                },
                "2": {
                    "1": "對",
                    "2": "曰"
                },
                "3": {
                    "1": "吾",
                    "2": "斯",
                    "3": "之",
                    "4": "未",
                    "5": "能",
                    "6": "信"
                },
                "4": {
                    "1": "子",
                    "2": "說"
                }
            }
        },
        "7": {
            "15": {
                "1": {
                    "1": "子",
                    "2": "曰"
                },
                "2": {
                    "1": "道",
                    "2": "不",
                    "3": "行"
                },
                "3": {
                    "1": "乘",
                    "2": "桴",
                    "3": "浮",
                    "4": "於",
                    "5": "海"
                },
                "4": {
                    "1": "從",
                    "2": "我",
                    "3": "者"
                },
                "5": {
                    "1": "其",
                    "2": "由",
                    "3": "與"
                },
                "6": {
                    "1": "子",
                    "2": "路",
                    "3": "聞",
                    "4": "之",
                    "5": "喜"
                },
                "7": {
                    "1": "子",
                    "2": "曰"
                },
                "8": {
                    "1": "由",
                    "2": "也",
                    "3": "好",
                    "4": "勇",
                    "5": "過",
                    "6": "我"
                },
                "9": {
                    "1": "無",
                    "2": "所",
                    "3": "取",
                    "4": "材"
                }
            }
        },
        "8": {
            "17": {
                "1": {
                    "1": "孟",
                    "2": "武",
                    "3": "伯",
                    "4": "問"
                },
                "2": {
                    "1": "子",
                    "2": "路",
                    "3": "仁",
                    "4": "乎"
                },
                "3": {
                    "1": "子",
                    "2": "曰"
                },
                "4": {
                    "1": "不",
                    "2": "知",
                    "3": "也"
                },
                "5": {
                    "1": "又",
                    "2": "問"
                },
                "6": {
                    "1": "子",
                    "2": "曰"
                },
                "7": {
                    "1": "由",
                    "2": "也"
                },
                "8": {
                    "1": "千",
                    "2": "乘",
                    "3": "之",
                    "4": "國"
                },
                "9": {
                    "1": "可",
                    "2": "使",
                    "3": "治",
                    "4": "其",
                    "5": "賦",
                    "6": "也"
                },
                "10": {
                    "1": "不",
                    "2": "知",
                    "3": "其",
                    "4": "仁",
                    "5": "也"
                },
                "11": {
                    "1": "求",
                    "2": "也",
                    "3": "何",
                    "4": "如"
                },
                "12": {
                    "1": "子",
                    "2": "曰"
                },
                "13": {
                    "1": "求",
                    "2": "也"
                },
                "14": {
                    "1": "千",
                    "2": "室",
                    "3": "之",
                    "4": "邑"
                },
                "15": {
                    "1": "百",
                    "2": "乘",
                    "3": "之",
                    "4": "家"
                },
                "16": {
                    "1": "可",
                    "2": "使",
                    "3": "爲",
                    "4": "之",
                    "5": "宰",
                    "6": "也"
                },
                "17": {
                    "1": "不",
                    "2": "知",
                    "3": "其",
                    "4": "仁",
                    "5": "也"
                },
                "18": {
                    "1": "赤",
                    "2": "也",
                    "3": "何",
                    "4": "如"
                },
                "19": {
                    "1": "子",
                    "2": "曰"
                },
                "20": {
                    "1": "赤",
                    "2": "也"
                },
                "21": {
                    "1": "束",
                    "2": "帶",
                    "3": "立",
                    "4": "於",
                    "5": "朝"
                },
                "22": {
                    "1": "可",
                    "2": "使",
                    "3": "與",
                    "4": "賓",
                    "5": "客",
                    "6": "言",
                    "7": "也"
                },
                "23": {
                    "1": "不",
                    "2": "知",
                    "3": "其",
                    "4": "仁",
                    "5": "也"
                }
            }
        },
        "9": {
            "19": {
                "1": {
                    "1": "子",
                    "2": "謂",
                    "3": "子",
                    "4": "貢",
                    "5": "曰"
                },
                "2": {
                    "1": "女",
                    "2": "與",
                    "3": "回",
                    "4": "也",
                    "5": "孰",
                    "6": "愈"
                },
                "3": {
                    "1": "對",
                    "2": "曰"
                },
                "4": {
                    "1": "賜",
                    "2": "也",
                    "3": "何",
                    "4": "敢",
                    "5": "望",
                    "6": "回"
                },
                "5": {
                    "1": "回",
                    "2": "也",
                    "3": "聞",
                    "4": "一",
                    "5": "以",
                    "6": "知",
                    "7": "十"
                },
                "6": {
                    "1": "賜",
                    "2": "也",
                    "3": "聞",
                    "4": "一",
                    "5": "以",
                    "6": "知",
                    "7": "二"
                }
            },
            "20": {
                "1": {
                    "1": "子",
                    "2": "曰"
                },
                "2": {
                    "1": "弗",
                    "2": "如",
                    "3": "也"
                },
                "3": {
                    "1": "吾",
                    "2": "與",
                    "3": "女",
                    "4": "弗",
                    "5": "如",
                    "6": "也"
                }
            }
        },
        "10": {
            "22": {
                "1": {
                    "1": "宰",
                    "2": "予",
                    "3": "晝",
                    "4": "寢"
                },
                "2": {
                    "1": "子",
                    "2": "曰"
                },
                "3": {
                    "1": "朽",
                    "2": "木",
                    "3": "不",
                    "4": "可",
                    "5": "雕",
                    "6": "也"
                },
                "4": {
                    "1": "糞",
                    "2": "土",
                    "3": "之",
                    "4": "牆",
                    "5": "不",
                    "6": "可",
                    "7": "杇",
                    "8": "也"
                },
                "5": {
                    "1": "於",
                    "2": "予",
                    "3": "與",
                    "4": "何",
                    "5": "誅"
                },
                "6": {
                    "1": "子",
                    "2": "曰"
                },
                "7": {
                    "1": "始",
                    "2": "吾",
                    "3": "於",
                    "4": "人",
                    "5": "也"
                },
                "8": {
                    "1": "聽",
                    "2": "其",
                    "3": "言",
                    "4": "而",
                    "5": "信",
                    "6": "其",
                    "7": "行"
                },
                "9": {
                    "1": "今",
                    "2": "吾",
                    "3": "於",
                    "4": "人",
                    "5": "也"
                },
                "10": {
                    "1": "聽",
                    "2": "其",
                    "3": "言",
                    "4": "而",
                    "5": "觀",
                    "6": "其",
                    "7": "行"
                },
                "11": {
                    "1": "於",
                    "2": "予",
                    "3": "與",
                    "4": "改",
                    "5": "是"
                }
            }
        },
        "11": {
            "24": {
                "1": {
                    "1": "子",
                    "2": "曰"
                },
                "2": {
                    "1": "吾",
                    "2": "未",
                    "3": "見",
                    "4": "剛",
                    "5": "者"
                },
                "3": {
                    "1": "或",
                    "2": "對",
                    "3": "曰"
                },
                "4": {
                    "1": "申",
                    "2": "棖"
                },
                "5": {
                    "1": "子",
                    "2": "曰"
                },
                "6": {
                    "1": "棖",
                    "2": "也",
                    "3": "慾"
                },
                "7": {
                    "1": "焉",
                    "2": "得",
                    "3": "剛"
                }
            }
        },
        "12": {
            "26": {
                "1": {
                    "1": "子",
                    "2": "貢",
                    "3": "曰"
                },
                "2": {
                    "1": "我",
                    "2": "不",
                    "3": "欲",
                    "4": "人",
                    "5": "之",
                    "6": "加",
                    "7": "諸",
                    "8": "我",
                    "9": "也"
                },
                "3": {
                    "1": "吾",
                    "2": "亦",
                    "3": "欲",
                    "4": "無",
                    "5": "加",
                    "6": "諸",
                    "7": "人"
                },
                "4": {
                    "1": "子",
                    "2": "曰"
                },
                "5": {
                    "1": "賜",
                    "2": "也"
                },
                "6": {
                    "1": "非",
                    "2": "爾",
                    "3": "所",
                    "4": "及",
                    "5": "也"
                }
            }
        },
        "13": {
            "28": {
                "1": {
                    "1": "子",
                    "2": "貢",
                    "3": "曰"
                },
                "2": {
                    "1": "夫",
                    "2": "子",
                    "3": "之",
                    "4": "文",
                    "5": "章"
                },
                "3": {
                    "1": "可",
                    "2": "得",
                    "3": "而",
                    "4": "聞",
                    "5": "也"
                },
                "4": {
                    "1": "夫",
                    "2": "子",
                    "3": "之",
                    "4": "言",
                    "5": "性",
                    "6": "與",
                    "7": "天",
                    "8": "道"
                },
                "5": {
                    "1": "不",
                    "2": "可",
                    "3": "得",
                    "4": "而",
                    "5": "聞",
                    "6": "也"
                }
            }
        },
        "14": {
            "30": {
                "1": {
                    "1": "子",
                    "2": "路",
                    "3": "有",
                    "4": "聞"
                },
                "2": {
                    "1": "未",
                    "2": "之",
                    "3": "能",
                    "4": "行"
                },
                "3": {
                    "1": "唯",
                    "2": "恐",
                    "3": "有",
                    "4": "聞"
                }
            }
        },
        "15": {
            "32": {
                "1": {
                    "1": "子",
                    "2": "貢",
                    "3": "問",
                    "4": "曰"
                },
                "2": {
                    "1": "孔",
                    "2": "文",
                    "3": "子",
                    "4": "何",
                    "5": "以",
                    "6": "謂",
                    "7": "之",
                    "8": "文",
                    "9": "也"
                },
                "3": {
                    "1": "子",
                    "2": "曰"
                },
                "4": {
                    "1": "敏",
                    "2": "而",
                    "3": "好",
                    "4": "學"
                },
                "5": {
                    "1": "不",
                    "2": "恥",
                    "3": "下",
                    "4": "問"
                },
                "6": {
                    "1": "是",
                    "2": "以",
                    "3": "謂",
                    "4": "之",
                    "5": "文",
                    "6": "也"
                }
            }
        },
        "16": {
            "34": {
                "1": {
                    "1": "子",
                    "2": "謂",
                    "3": "子",
                    "4": "產"
                },
                "2": {
                    "1": "有",
                    "2": "君",
                    "3": "子",
                    "4": "之",
                    "5": "道",
                    "6": "四",
                    "7": "焉"
                },
                "3": {
                    "1": "其",
                    "2": "行",
                    "3": "己",
                    "4": "也",
                    "5": "恭"
                },
                "4": {
                    "1": "其",
                    "2": "事",
                    "3": "上",
                    "4": "也",
                    "5": "敬"
                },
                "5": {
                    "1": "其",
                    "2": "養",
                    "3": "民",
                    "4": "也",
                    "5": "惠"
                },
                "6": {
                    "1": "其",
                    "2": "使",
                    "3": "民",
                    "4": "也",
                    "5": "義"
                }
            }
        },
        "17": {
            "36": {
                "1": {
                    "1": "子",
                    "2": "曰"
                },
                "2": {
                    "1": "晏",
                    "2": "平",
                    "3": "仲",
                    "4": "善",
                    "5": "與",
                    "6": "人",
                    "7": "交"
                },
                "3": {
                    "1": "久",
                    "2": "而",
                    "3": "敬",
                    "4": "之"
                }
            }
        },
        "18": {
            "38": {
                "1": {
                    "1": "子",
                    "2": "曰"
                },
                "2": {
                    "1": "臧",
                    "2": "文",
                    "3": "仲",
                    "4": "居",
                    "5": "蔡"
                },
                "3": {
                    "1": "山",
                    "2": "節",
                    "3": "藻",
                    "4": "梲"
                },
                "4": {
                    "1": "何",
                    "2": "如",
                    "3": "其",
                    "4": "知",
                    "5": "也"
                }
            }
        },
        "19": {
            "40": {
                "1": {
                    "1": "子",
                    "2": "張",
                    "3": "問",
                    "4": "曰"
                },
                "2": {
                    "1": "令",
                    "2": "尹",
                    "3": "子",
                    "4": "文",
                    "5": "三",
                    "6": "仕",
                    "7": "爲",
                    "8": "令",
                    "9": "尹"
                },
                "3": {
                    "1": "無",
                    "2": "喜",
                    "3": "色"
                },
                "4": {
                    "1": "三",
                    "2": "已",
                    "3": "之"
                },
                "5": {
                    "1": "無",
                    "2": "慍",
                    "3": "色"
                },
                "6": {
                    "1": "舊",
                    "2": "令",
                    "3": "尹",
                    "4": "之",
                    "5": "政"
                },
                "7": {
                    "1": "必",
                    "2": "以",
                    "3": "告",
                    "4": "新",
                    "5": "令",
                    "6": "尹"
                },
                "8": {
                    "1": "何",
                    "2": "如"
                },
                "9": {
                    "1": "子",
                    "2": "曰"
                },
                "10": {
                    "1": "忠",
                    "2": "矣"
                },
                "11": {
                    "1": "曰"
                },
                "12": {
                    "1": "仁",
                    "2": "矣",
                    "3": "乎"
                },
                "13": {
                    "1": "曰"
                },
                "14": {
                    "1": "未",
                    "2": "知"
                },
                "15": {
                    "1": "焉",
                    "2": "得",
                    "3": "仁"
                },
                "16": {
                    "1": "崔",
                    "2": "子",
                    "3": "弒",
                    "4": "齊",
                    "5": "君"
                },
                "17": {
                    "1": "陳",
                    "2": "文",
                    "3": "子",
                    "4": "有",
                    "5": "馬",
                    "6": "十",
                    "7": "乘"
                },
                "18": {
                    "1": "棄",
                    "2": "而",
                    "3": "違",
                    "4": "之"
                },
                "19": {
                    "1": "至",
                    "2": "於",
                    "3": "他",
                    "4": "邦"
                },
                "20": {
                    "1": "則",
                    "2": "曰"
                },
                "21": {
                    "1": "猶",
                    "2": "吾",
                    "3": "大",
                    "4": "夫",
                    "5": "崔",
                    "6": "子",
                    "7": "也"
                },
                "22": {
                    "1": "違",
                    "2": "之"
                },
                "23": {
                    "1": "之",
                    "2": "一",
                    "3": "邦"
                },
                "24": {
                    "1": "則",
                    "2": "又",
                    "3": "曰"
                },
                "25": {
                    "1": "猶",
                    "2": "吾",
                    "3": "大",
                    "4": "夫",
                    "5": "崔",
                    "6": "子",
                    "7": "也"
                },
                "26": {
                    "1": "違",
                    "2": "之"
                },
                "27": {
                    "1": "何",
                    "2": "如"
                },
                "28": {
                    "1": "子",
                    "2": "曰"
                },
                "29": {
                    "1": "清",
                    "2": "矣"
                },
                "30": {
                    "1": "曰"
                },
                "31": {
                    "1": "仁",
                    "2": "矣",
                    "3": "乎"
                },
                "32": {
                    "1": "曰"
                },
                "33": {
                    "1": "未",
                    "2": "知"
                },
                "34": {
                    "1": "焉",
                    "2": "得",
                    "3": "仁"
                }
            }
        },
        "20": {
            "42": {
                "1": {
                    "1": "季",
                    "2": "文",
                    "3": "子",
                    "4": "三",
                    "5": "思",
                    "6": "而",
                    "7": "後",
                    "8": "行"
                },
                "2": {
                    "1": "子",
                    "2": "聞",
                    "3": "之"
                },
                "3": {
                    "1": "曰"
                },
                "4": {
                    "1": "再"
                },
                "5": {
                    "1": "斯",
                    "2": "可",
                    "3": "矣"
                }
            }
        },
        "21": {
            "44": {
                "1": {
                    "1": "子",
                    "2": "曰"
                },
                "2": {
                    "1": "甯",
                    "2": "武",
                    "3": "子"
                },
                "3": {
                    "1": "邦",
                    "2": "有",
                    "3": "道",
                    "4": "則",
                    "5": "知"
                },
                "4": {
                    "1": "邦",
                    "2": "無",
                    "3": "道",
                    "4": "則",
                    "5": "愚"
                },
                "5": {
                    "1": "其",
                    "2": "知",
                    "3": "可",
                    "4": "及",
                    "5": "也"
                },
                "6": {
                    "1": "其",
                    "2": "愚",
                    "3": "不",
                    "4": "可",
                    "5": "及",
                    "6": "也"
                }
            }
        },
        "22": {
            "46": {
                "1": {
                    "1": "子",
                    "2": "在",
                    "3": "陳"
                },
                "2": {
                    "1": "曰"
                },
                "3": {
                    "1": "歸",
                    "2": "與"
                },
                "4": {
                    "1": "歸",
                    "2": "與"
                },
                "5": {
                    "1": "吾",
                    "2": "黨",
                    "3": "之",
                    "4": "小",
                    "5": "子",
                    "6": "狂",
                    "7": "簡"
                },
                "6": {
                    "1": "斐",
                    "2": "然",
                    "3": "成",
                    "4": "章"
                },
                "7": {
                    "1": "不",
                    "2": "知",
                    "3": "所",
                    "4": "以",
                    "5": "裁",
                    "6": "之"
                }
            }
        },
        "23": {
            "48": {
                "1": {
                    "1": "子",
                    "2": "曰"
                },
                "2": {
                    "1": "伯",
                    "2": "夷"
                },
                "3": {
                    "1": "叔",
                    "2": "齊",
                    "3": "不",
                    "4": "念",
                    "5": "舊",
                    "6": "惡"
                },
                "4": {
                    "1": "怨",
                    "2": "是",
                    "3": "用",
                    "4": "希"
                }
            }
        },
        "24": {
            "50": {
                "1": {
                    "1": "子",
                    "2": "曰"
                },
                "2": {
                    "1": "孰",
                    "2": "謂",
                    "3": "微",
                    "4": "生",
                    "5": "高",
                    "6": "直"
                },
                "3": {
                    "1": "或",
                    "2": "乞",
                    "3": "醯",
                    "4": "焉"
                },
                "4": {
                    "1": "乞",
                    "2": "諸",
                    "3": "其",
                    "4": "鄰",
                    "5": "而",
                    "6": "與",
                    "7": "之"
                }
            }
        },
        "25": {
            "52": {
                "1": {
                    "1": "子",
                    "2": "曰"
                },
                "2": {
                    "1": "巧",
                    "2": "言"
                },
                "3": {
                    "1": "令",
                    "2": "色"
                },
                "4": {
                    "1": "足",
                    "2": "恭"
                },
                "5": {
                    "1": "左",
                    "2": "丘",
                    "3": "明",
                    "4": "恥",
                    "5": "之"
                },
                "6": {
                    "1": "丘",
                    "2": "亦",
                    "3": "恥",
                    "4": "之"
                },
                "7": {
                    "1": "匿",
                    "2": "怨",
                    "3": "而",
                    "4": "友",
                    "5": "其",
                    "6": "人"
                },
                "8": {
                    "1": "左",
                    "2": "丘",
                    "3": "明",
                    "4": "恥",
                    "5": "之"
                },
                "9": {
                    "1": "丘",
                    "2": "亦",
                    "3": "恥",
                    "4": "之"
                }
            }
        },
        "26": {
            "54": {
                "1": {
                    "1": "顏",
                    "2": "淵"
                },
                "2": {
                    "1": "季",
                    "2": "路",
                    "3": "侍"
                },
                "3": {
                    "1": "子",
                    "2": "曰"
                },
                "4": {
                    "1": "盍",
                    "2": "各",
                    "3": "言",
                    "4": "爾",
                    "5": "志"
                },
                "5": {
                    "1": "子",
                    "2": "路",
                    "3": "曰"
                },
                "6": {
                    "1": "願",
                    "2": "車",
                    "3": "馬",
                    "4": "衣",
                    "5": "輕",
                    "6": "裘"
                },
                "7": {
                    "1": "與",
                    "2": "朋",
                    "3": "友",
                    "4": "共"
                },
                "8": {
                    "1": "敝",
                    "2": "之",
                    "3": "而",
                    "4": "無",
                    "5": "憾"
                },
                "9": {
                    "1": "顏",
                    "2": "淵",
                    "3": "曰"
                },
                "10": {
                    "1": "願",
                    "2": "無",
                    "3": "伐",
                    "4": "善"
                },
                "11": {
                    "1": "無",
                    "2": "施",
                    "3": "勞"
                },
                "12": {
                    "1": "子",
                    "2": "路",
                    "3": "曰"
                },
                "13": {
                    "1": "願",
                    "2": "聞",
                    "3": "子",
                    "4": "之",
                    "5": "志"
                },
                "14": {
                    "1": "子",
                    "2": "曰"
                },
                "15": {
                    "1": "老",
                    "2": "者",
                    "3": "安",
                    "4": "之"
                },
                "16": {
                    "1": "朋",
                    "2": "友",
                    "3": "信",
                    "4": "之"
                },
                "17": {
                    "1": "少",
                    "2": "者",
                    "3": "懷",
                    "4": "之"
                }
            }
        },
        "27": {
            "56": {
                "1": {
                    "1": "子",
                    "2": "曰"
                },
                "2": {
                    "1": "已",
                    "2": "矣",
                    "3": "乎"
                },
                "3": {
                    "1": "吾",
                    "2": "未",
                    "3": "見",
                    "4": "能",
                    "5": "見",
                    "6": "其",
                    "7": "過",
                    "8": "而",
                    "9": "內",
                    "10": "自",
                    "11": "訟",
                    "12": "者",
                    "13": "也"
                }
            }
        },
        "28": {
            "58": {
                "1": {
                    "1": "子",
                    "2": "曰"
                },
                "2": {
                    "1": "十",
                    "2": "室",
                    "3": "之",
                    "4": "邑"
                },
                "3": {
                    "1": "必",
                    "2": "有",
                    "3": "忠",
                    "4": "信",
                    "5": "如",
                    "6": "丘",
                    "7": "者",
                    "8": "焉"
                },
                "4": {
                    "1": "不",
                    "2": "如",
                    "3": "丘",
                    "4": "之",
                    "5": "好",
                    "6": "學",
                    "7": "也"
                }
            }
        }
    }
}