{
    "13.05": {
        "篇名": "賈誼 鵩鳥賦[幷序]",
        "1": {
            "3": {
                "1": {
                    "1": "誼",
                    "2": "爲",
                    "3": "長",
                    "4": "沙",
                    "5": "王",
                    "6": "傅",
                    "7": "三",
                    "8": "年"
                },
                "2": {
                    "1": "有",
                    "2": "鵩",
                    "3": "鳥",
                    "4": "飛",
                    "5": "入",
                    "6": "誼",
                    "7": "舍"
                },
                "3": {
                    "1": "止",
                    "2": "於",
                    "3": "坐",
                    "4": "隅"
                },
                "4": {
                    "1": "鵩",
                    "2": "似",
                    "3": "鴞"
                },
                "5": {
                    "1": "不",
                    "2": "祥",
                    "3": "鳥",
                    "4": "也"
                },
                "6": {
                    "1": "誼",
                    "2": "旣",
                    "3": "以",
                    "4": "謫",
                    "5": "居",
                    "6": "長",
                    "7": "沙"
                },
                "7": {
                    "1": "長",
                    "2": "沙",
                    "3": "卑",
                    "4": "濕"
                },
                "8": {
                    "1": "誼",
                    "2": "自",
                    "3": "傷",
                    "4": "悼"
                },
                "9": {
                    "1": "以",
                    "2": "爲",
                    "3": "壽",
                    "4": "不",
                    "5": "得",
                    "6": "長"
                },
                "10": {
                    "1": "迺",
                    "2": "爲",
                    "3": "賦",
                    "4": "以",
                    "5": "自",
                    "6": "廣"
                },
                "11": {
                    "1": "其",
                    "2": "辭",
                    "3": "曰"
                }
            }
        },
        "2": {
            "5": {
                "1": {
                    "1": "單",
                    "2": "閼",
                    "3": "之",
                    "4": "歲"
                },
                "2": {
                    "1": "四",
                    "2": "月",
                    "3": "孟",
                    "4": "夏"
                },
                "3": {
                    "1": "庚",
                    "2": "子",
                    "3": "日",
                    "4": "斜"
                },
                "4": {
                    "1": "鵩",
                    "2": "集",
                    "3": "余",
                    "4": "舍"
                },
                "5": {
                    "1": "止",
                    "2": "於",
                    "3": "坐",
                    "4": "隅"
                },
                "6": {
                    "1": "貌",
                    "2": "甚",
                    "3": "間",
                    "4": "暇"
                },
                "7": {
                    "1": "異",
                    "2": "物",
                    "3": "來",
                    "4": "崒"
                },
                "8": {
                    "1": "私",
                    "2": "怪",
                    "3": "其",
                    "4": "故"
                },
                "9": {
                    "1": "發",
                    "2": "書",
                    "3": "占",
                    "4": "之"
                },
                "10": {
                    "1": "讖",
                    "2": "言",
                    "3": "其",
                    "4": "度"
                },
                "11": {
                    "1": "曰",
                    "2": "野",
                    "3": "鳥",
                    "4": "入",
                    "5": "室"
                },
                "12": {
                    "1": "主",
                    "2": "人",
                    "3": "將",
                    "4": "去"
                },
                "13": {
                    "1": "問",
                    "2": "於",
                    "3": "子",
                    "4": "鵩"
                },
                "14": {
                    "1": "余",
                    "2": "去",
                    "3": "何",
                    "4": "之"
                },
                "15": {
                    "1": "吉",
                    "2": "虖",
                    "3": "告",
                    "4": "我"
                },
                "16": {
                    "1": "凶",
                    "2": "言",
                    "3": "其",
                    "4": "災"
                },
                "17": {
                    "1": "淹",
                    "2": "速",
                    "3": "之",
                    "4": "度"
                },
                "18": {
                    "1": "語",
                    "2": "余",
                    "3": "其",
                    "4": "期"
                }
            }
        },
        "3": {
            "7": {
                "1": {
                    "1": "鵩",
                    "2": "乃",
                    "3": "太",
                    "4": "息"
                },
                "2": {
                    "1": "舉",
                    "2": "首",
                    "3": "奮",
                    "4": "翼"
                },
                "3": {
                    "1": "口",
                    "2": "不",
                    "3": "能",
                    "4": "言"
                },
                "4": {
                    "1": "請",
                    "2": "對",
                    "3": "以",
                    "4": "意"
                },
                "5": {
                    "1": "萬",
                    "2": "物",
                    "3": "變",
                    "4": "化"
                },
                "6": {
                    "1": "固",
                    "2": "亡",
                    "3": "休",
                    "4": "息"
                },
                "7": {
                    "1": "斡",
                    "2": "流",
                    "3": "而",
                    "4": "遷"
                },
                "8": {
                    "1": "或",
                    "2": "推",
                    "3": "而",
                    "4": "還"
                },
                "9": {
                    "1": "形",
                    "2": "氣",
                    "3": "轉",
                    "4": "續"
                },
                "10": {
                    "1": "變",
                    "2": "化",
                    "3": "而",
                    "4": "嬗"
                },
                "11": {
                    "1": "沕",
                    "2": "穆",
                    "3": "亡",
                    "4": "間"
                },
                "12": {
                    "1": "胡",
                    "2": "可",
                    "3": "勝",
                    "4": "言"
                },
                "13": {
                    "1": "禍",
                    "2": "兮",
                    "3": "福",
                    "4": "所",
                    "5": "倚"
                },
                "14": {
                    "1": "福",
                    "2": "兮",
                    "3": "禍",
                    "4": "所",
                    "5": "伏"
                },
                "15": {
                    "1": "憂",
                    "2": "喜",
                    "3": "聚",
                    "4": "門"
                },
                "16": {
                    "1": "吉",
                    "2": "凶",
                    "3": "同",
                    "4": "域"
                },
                "17": {
                    "1": "彼",
                    "2": "吳",
                    "3": "彊",
                    "4": "大"
                },
                "18": {
                    "1": "夫",
                    "2": "差",
                    "3": "以",
                    "4": "敗"
                },
                "19": {
                    "1": "粵",
                    "2": "栖",
                    "3": "會",
                    "4": "稽"
                },
                "20": {
                    "1": "句",
                    "2": "踐",
                    "3": "伯",
                    "4": "世"
                },
                "21": {
                    "1": "斯",
                    "2": "遊",
                    "3": "遂",
                    "4": "成"
                },
                "22": {
                    "1": "卒",
                    "2": "被",
                    "3": "五",
                    "4": "刑"
                },
                "23": {
                    "1": "傅",
                    "2": "說",
                    "3": "胥",
                    "4": "靡"
                },
                "24": {
                    "1": "乃",
                    "2": "相",
                    "3": "武",
                    "4": "丁"
                },
                "25": {
                    "1": "夫",
                    "2": "禍",
                    "3": "之",
                    "4": "與",
                    "5": "福"
                },
                "26": {
                    "1": "何",
                    "2": "異",
                    "3": "糾",
                    "4": "纆"
                },
                "27": {
                    "1": "命",
                    "2": "不",
                    "3": "可",
                    "4": "說"
                },
                "28": {
                    "1": "孰",
                    "2": "知",
                    "3": "其",
                    "4": "極"
                },
                "29": {
                    "1": "水",
                    "2": "激",
                    "3": "則",
                    "4": "旱"
                },
                "30": {
                    "1": "矢",
                    "2": "激",
                    "3": "則",
                    "4": "遠"
                },
                "31": {
                    "1": "萬",
                    "2": "物",
                    "3": "回",
                    "4": "薄"
                },
                "32": {
                    "1": "震",
                    "2": "蕩",
                    "3": "相",
                    "4": "轉"
                },
                "33": {
                    "1": "雲",
                    "2": "烝",
                    "3": "雨",
                    "4": "降"
                },
                "34": {
                    "1": "糾",
                    "2": "錯",
                    "3": "相",
                    "4": "紛"
                },
                "35": {
                    "1": "大",
                    "2": "鈞",
                    "3": "播",
                    "4": "物"
                },
                "36": {
                    "1": "坱",
                    "2": "圠",
                    "3": "無",
                    "4": "垠"
                },
                "37": {
                    "1": "天",
                    "2": "不",
                    "3": "可",
                    "4": "與",
                    "5": "慮"
                },
                "38": {
                    "1": "道",
                    "2": "不",
                    "3": "可",
                    "4": "與",
                    "5": "謀"
                },
                "39": {
                    "1": "遲",
                    "2": "速",
                    "3": "有",
                    "4": "命"
                },
                "40": {
                    "1": "烏",
                    "2": "識",
                    "3": "其",
                    "4": "時"
                }
            }
        },
        "4": {
            "9": {
                "1": {
                    "1": "且",
                    "2": "夫",
                    "3": "天",
                    "4": "地",
                    "5": "爲",
                    "6": "爐"
                },
                "2": {
                    "1": "造",
                    "2": "化",
                    "3": "爲",
                    "4": "工"
                },
                "3": {
                    "1": "陰",
                    "2": "陽",
                    "3": "爲",
                    "4": "炭"
                },
                "4": {
                    "1": "萬",
                    "2": "物",
                    "3": "爲",
                    "4": "銅"
                },
                "5": {
                    "1": "合",
                    "2": "散",
                    "3": "消",
                    "4": "息"
                },
                "6": {
                    "1": "安",
                    "2": "有",
                    "3": "常",
                    "4": "則"
                },
                "7": {
                    "1": "千",
                    "2": "變",
                    "3": "萬",
                    "4": "化"
                },
                "8": {
                    "1": "未",
                    "2": "始",
                    "3": "有",
                    "4": "極"
                },
                "9": {
                    "1": "忽",
                    "2": "然",
                    "3": "爲",
                    "4": "人"
                },
                "10": {
                    "1": "何",
                    "2": "足",
                    "3": "控",
                    "4": "揣"
                },
                "11": {
                    "1": "化",
                    "2": "爲",
                    "3": "異",
                    "4": "物"
                },
                "12": {
                    "1": "又",
                    "2": "何",
                    "3": "足",
                    "4": "患"
                },
                "13": {
                    "1": "小",
                    "2": "智",
                    "3": "自",
                    "4": "私"
                },
                "14": {
                    "1": "賤",
                    "2": "彼",
                    "3": "貴",
                    "4": "我"
                },
                "15": {
                    "1": "達",
                    "2": "人",
                    "3": "大",
                    "4": "觀"
                },
                "16": {
                    "1": "物",
                    "2": "亡",
                    "3": "不",
                    "4": "可"
                },
                "17": {
                    "1": "貪",
                    "2": "夫",
                    "3": "徇",
                    "4": "財"
                },
                "18": {
                    "1": "列",
                    "2": "士",
                    "3": "徇",
                    "4": "名"
                },
                "19": {
                    "1": "夸",
                    "2": "者",
                    "3": "死",
                    "4": "權"
                },
                "20": {
                    "1": "品",
                    "2": "庶",
                    "3": "每",
                    "4": "生"
                },
                "21": {
                    "1": "怵",
                    "2": "迫",
                    "3": "之",
                    "4": "徒"
                },
                "22": {
                    "1": "或",
                    "2": "趨",
                    "3": "西",
                    "4": "東"
                },
                "23": {
                    "1": "大",
                    "2": "人",
                    "3": "不",
                    "4": "曲"
                },
                "24": {
                    "1": "意",
                    "2": "變",
                    "3": "齊",
                    "4": "同"
                },
                "25": {
                    "1": "愚",
                    "2": "士",
                    "3": "繫",
                    "4": "俗"
                },
                "26": {
                    "1": "時",
                    "2": "若",
                    "3": "囚",
                    "4": "拘"
                },
                "27": {
                    "1": "至",
                    "2": "人",
                    "3": "遺",
                    "4": "物"
                },
                "28": {
                    "1": "獨",
                    "2": "與",
                    "3": "道",
                    "4": "俱"
                },
                "29": {
                    "1": "眾",
                    "2": "人",
                    "3": "惑",
                    "4": "惑"
                },
                "30": {
                    "1": "好",
                    "2": "惡",
                    "3": "積",
                    "4": "意"
                },
                "31": {
                    "1": "眞",
                    "2": "人",
                    "3": "恬",
                    "4": "漠"
                },
                "32": {
                    "1": "獨",
                    "2": "與",
                    "3": "道",
                    "4": "息"
                },
                "33": {
                    "1": "釋",
                    "2": "智",
                    "3": "遺",
                    "4": "形"
                },
                "34": {
                    "1": "超",
                    "2": "然",
                    "3": "自",
                    "4": "喪"
                },
                "35": {
                    "1": "寥",
                    "2": "廓",
                    "3": "忽",
                    "4": "荒"
                },
                "36": {
                    "1": "與",
                    "2": "道",
                    "3": "翱",
                    "4": "翔"
                },
                "37": {
                    "1": "乘",
                    "2": "流",
                    "3": "則",
                    "4": "逝"
                },
                "38": {
                    "1": "得",
                    "2": "坎",
                    "3": "則",
                    "4": "止"
                },
                "39": {
                    "1": "縱",
                    "2": "軀",
                    "3": "委",
                    "4": "命"
                },
                "40": {
                    "1": "不",
                    "2": "私",
                    "3": "與",
                    "4": "己"
                },
                "41": {
                    "1": "其",
                    "2": "生",
                    "3": "兮",
                    "4": "若",
                    "5": "浮"
                },
                "42": {
                    "1": "其",
                    "2": "死",
                    "3": "兮",
                    "4": "若",
                    "5": "休"
                },
                "43": {
                    "1": "澹",
                    "2": "虖",
                    "3": "若",
                    "4": "深",
                    "5": "淵",
                    "6": "之",
                    "7": "靚"
                },
                "44": {
                    "1": "泛",
                    "2": "虖",
                    "3": "若",
                    "4": "不",
                    "5": "繫",
                    "6": "之",
                    "7": "舟"
                },
                "45": {
                    "1": "不",
                    "2": "以",
                    "3": "生",
                    "4": "故",
                    "5": "自",
                    "6": "保"
                },
                "46": {
                    "1": "養",
                    "2": "空",
                    "3": "而",
                    "4": "浮"
                },
                "47": {
                    "1": "德",
                    "2": "人",
                    "3": "無",
                    "4": "累"
                },
                "48": {
                    "1": "知",
                    "2": "命",
                    "3": "不",
                    "4": "憂"
                },
                "49": {
                    "1": "細",
                    "2": "故",
                    "3": "蔕",
                    "4": "芥"
                },
                "50": {
                    "1": "何",
                    "2": "足",
                    "3": "以",
                    "4": "疑"
                }
            }
        }
    }
}