{
    "30.31-05": {
        "篇名": "謝靈運 擬魏太子鄴中集詩八首[幷序]·劉楨",
        "1": {
            "3": {
                "1": "卓犖偏人",
                "2": "而文最有氣",
                "3": "所得頗經奇"
            },
            "4": {
                "1": "貧居晏里閈",
                "2": "少小長東平",
                "3": "河兗當衝要",
                "4": "淪飄薄許京",
                "5": "廣川無逆流",
                "6": "招納廁羣英",
                "7": "北渡黎陽津",
                "8": "南登紀郢城",
                "9": "旣覽古今事",
                "10": "頗識治亂情",
                "11": "歡友相解達",
                "12": "敷奏究平生",
                "13": "矧荷明哲顧",
                "14": "知深覺命輕",
                "15": "朝遊牛羊下",
                "16": "暮坐括揭鳴",
                "17": "終歲非一日",
                "18": "傳卮弄新聲",
                "19": "辰事旣難諧",
                "20": "歡願如今幷",
                "21": "唯羨肅肅翰",
                "22": "繽紛戾高冥"
            }
        }
    }
}